simerse/__init__.py
simerse/box_format.py
simerse/data_loader.py
simerse/data_writer.py
simerse/image_util.py
simerse/simerse_data_loader.py
simerse/simerse_keys.py
simerse/simerse_visualize.py
simerse/tonemapping.py
simerse-1.3.dist-info/METADATA
simerse-1.3.dist-info/WHEEL
simerse-1.3.dist-info/top_level.txt
simerse-1.3.dist-info/RECORD
