Metadata-Version: 2.1
Name: simerse
Version: 1.3
Summary: Simerse Dataset Loader and Visualizer
Home-page: https://www.simerse.com
Author: Simerse
Author-email: hauckjp@gmail.com
License: UNKNOWN
Platform: UNKNOWN
Classifier: Programming Language :: Python :: 3.8
Classifier: Operating System :: OS Independent
